README.md
setup.cfg
setup.py
tf_complex_channels/__init__.py
tf_complex_channels/transforms.py
tf_complex_channels.egg-info/PKG-INFO
tf_complex_channels.egg-info/SOURCES.txt
tf_complex_channels.egg-info/dependency_links.txt
tf_complex_channels.egg-info/top_level.txt