Metadata-Version: 2.1
Name: tf-complex-channels
Version: 0.0.1
Summary: A library to work with complex number deep learning.
Home-page: https://github.com/lukewood/tf-complex-channels
Author: Luke Wood
Author-email: lukewoodcs@gmail.com
License: MIT
Platform: UNKNOWN
